README.md
setup.py
secret_santa/__init__.py
secret_santa/secret_santa.py
secret_santa_handler.egg-info/PKG-INFO
secret_santa_handler.egg-info/SOURCES.txt
secret_santa_handler.egg-info/dependency_links.txt
secret_santa_handler.egg-info/top_level.txt