Metadata-Version: 2.1
Name: secret_santa_handler
Version: 0.0.2
Summary: A simple Secret Santa name matcher
Author: Atharva Rasane
Author-email: rratharva@gmail.com
Keywords: python,secret santa,random name matcher
Classifier: Development Status :: 5 - Production/Stable
Classifier: Intended Audience :: Developers
Classifier: Programming Language :: Python :: 3
Classifier: Operating System :: OS Independent
